{
  "client_documentation": "https://cloud.google.com/nodejs/docs/reference/binary-authorization/latest",
  "api_id": "binaryauthorization.googleapis.com",
  "distribution_name": "@google-cloud/binary-authorization",
  "release_level": "beta",
  "default_version": "v1beta1",
  "language": "nodejs",
  "name_pretty": "Binary Authorization",
  "repo": "googleapis/nodejs-binary-authorization",
  "product_documentation": "https://cloud.google.com/binary-authorization/",
  "requires_billing": true,
  "name": "binaryauthorization",
  "issue_tracker": "https://github.com/googleapis/nodejs-binary-authorization/issues",
  "codeowner_team": "@googleapis/cicd"
}
