{
  "language": "nodejs",
  "issue_tracker": "https://github.com/googleapis/nodejs-ai-platform/issues",
  "requires_billing": true,
  "name_pretty": "AI Platform",
  "product_documentation": "https://cloud.google.com/ai-platform/docs",
  "name": "aiplatform",
  "default_version": "v1",
  "client_documentation": "https://googleapis.dev/nodejs/aiplatform/latest",
  "release_level": "beta",
  "api_id": "aiplatform.googleapis.com",
  "repo": "googleapis/nodejs-ai-platform",
  "codeowner_team": "@googleapis/ml-apis",
  "distribution_name": "@google-cloud/aiplatform"
}
